easySQLite/SED.py
easySQLite/__init__.py
easySQLite/eSqlite.py
easySQLiteV2-0.11.dist-info/LICENSE
easySQLiteV2-0.11.dist-info/METADATA
easySQLiteV2-0.11.dist-info/WHEEL
easySQLiteV2-0.11.dist-info/top_level.txt
easySQLiteV2-0.11.dist-info/RECORD
