Metadata-Version: 2.1
Name: easySQLiteV2
Version: 0.11
Summary: This module to used to manage sqlite database with ease.
Home-page: https://github.com/harshnative/easySQLite
Author: Harsh Native
Author-email: Harshnative@gmail.com
License: UNKNOWN
Platform: UNKNOWN
Classifier: Programming Language :: Python :: 3
Classifier: License :: OSI Approved :: MIT License
Classifier: Operating System :: OS Independent
Requires-Python: >=3.6
Requires-Dist: tabulate
Requires-Dist: cryptography
Requires-Dist: onetimepad
